.DS_Store
LICENSE
MANIFEST.in
README.md
setup.py
RFDetect/.DS_Store
RFDetect/_init_.py
RFDetect/rfmodel-xss.pkl
RFDetect.egg-info/PKG-INFO
RFDetect.egg-info/SOURCES.txt
RFDetect.egg-info/dependency_links.txt
RFDetect.egg-info/top_level.txt
RFDetect/DataProcessing/.DS_Store
RFDetect/DataProcessing/DataProcessor.py
RFDetect/DataProcessing/MalwareDataProcessor.py
RFDetect/DataProcessing/NormalDataProcessor.py
RFDetect/DataProcessing/labeled_data.csv
RFDetect/DataProcessing/readme.txt
RFDetect/DataProcessing/test.py
RFDetect/DataProcessing/xss-20000.txt
RFDetect/DataProcessing/xss-train.txt
RFDetect/DataProcessing/.idea/DataProcessing.iml
RFDetect/DataProcessing/.idea/misc.xml
RFDetect/DataProcessing/.idea/modules.xml
RFDetect/DataProcessing/.idea/workspace.xml
RFDetect/DataProcessing/.idea/inspectionProfiles/profiles_settings.xml
RFDetect/DataProcessing/__pycache__/DataProcessor.cpython-37.pyc
RFDetect/DataProcessing/__pycache__/DataProcessor.cpython-38.pyc
RFDetect/DataProcessing/__pycache__/MalwareDataProcessor.cpython-37.pyc
RFDetect/DataProcessing/__pycache__/MalwareDataProcessor.cpython-38.pyc
RFDetect/DataProcessing/__pycache__/NormalDataProcessor.cpython-37.pyc
RFDetect/DataProcessing/__pycache__/NormalDataProcessor.cpython-38.pyc
RFDetect/DataProcessing/venv/LICENSE.txt
RFDetect/DataProcessing/venv/Include/Python-ast.h
RFDetect/DataProcessing/venv/Include/Python.h
RFDetect/DataProcessing/venv/Include/abstract.h
RFDetect/DataProcessing/venv/Include/asdl.h
RFDetect/DataProcessing/venv/Include/ast.h
RFDetect/DataProcessing/venv/Include/bitset.h
RFDetect/DataProcessing/venv/Include/boolobject.h
RFDetect/DataProcessing/venv/Include/bufferobject.h
RFDetect/DataProcessing/venv/Include/bytearrayobject.h
RFDetect/DataProcessing/venv/Include/bytes_methods.h
RFDetect/DataProcessing/venv/Include/bytesobject.h
RFDetect/DataProcessing/venv/Include/cStringIO.h
RFDetect/DataProcessing/venv/Include/cellobject.h
RFDetect/DataProcessing/venv/Include/ceval.h
RFDetect/DataProcessing/venv/Include/classobject.h
RFDetect/DataProcessing/venv/Include/cobject.h
RFDetect/DataProcessing/venv/Include/code.h
RFDetect/DataProcessing/venv/Lib/site-packages/pip-20.2.3.dist-info/INSTALLER
RFDetect/DataProcessing/venv/Lib/site-packages/pip-20.2.3.dist-info/LICENSE.txt
RFDetect/DataProcessing/venv/Lib/site-packages/pip-20.2.3.dist-info/METADATA
RFDetect/DataProcessing/venv/Lib/site-packages/pip-20.2.3.dist-info/RECORD
RFDetect/DataProcessing/venv/Lib/site-packages/pip-20.2.3.dist-info/WHEEL
RFDetect/DataProcessing/venv/Lib/site-packages/pip-20.2.3.dist-info/entry_points.txt
RFDetect/DataProcessing/venv/Lib/site-packages/pip-20.2.3.dist-info/top_level.txt
RFDetect/DataProcessing/venv/Lib/site-packages/setuptools-44.1.1.dist-info/INSTALLER
RFDetect/DataProcessing/venv/Lib/site-packages/setuptools-44.1.1.dist-info/LICENSE
RFDetect/DataProcessing/venv/Lib/site-packages/setuptools-44.1.1.dist-info/METADATA
RFDetect/DataProcessing/venv/Lib/site-packages/setuptools-44.1.1.dist-info/RECORD
RFDetect/DataProcessing/venv/Lib/site-packages/setuptools-44.1.1.dist-info/WHEEL
RFDetect/DataProcessing/venv/Lib/site-packages/setuptools-44.1.1.dist-info/dependency_links.txt
RFDetect/DataProcessing/venv/Lib/site-packages/setuptools-44.1.1.dist-info/entry_points.txt
RFDetect/DataProcessing/venv/Lib/site-packages/setuptools-44.1.1.dist-info/top_level.txt
RFDetect/DataProcessing/venv/Lib/site-packages/setuptools-44.1.1.dist-info/zip-safe
RFDetect/DataProcessing/venv/Lib/site-packages/wheel-0.35.1.dist-info/INSTALLER
RFDetect/DataProcessing/venv/Lib/site-packages/wheel-0.35.1.dist-info/LICENSE.txt
RFDetect/DataProcessing/venv/Lib/site-packages/wheel-0.35.1.dist-info/METADATA
RFDetect/DataProcessing/venv/Lib/site-packages/wheel-0.35.1.dist-info/RECORD
RFDetect/DataProcessing/venv/Lib/site-packages/wheel-0.35.1.dist-info/WHEEL
RFDetect/DataProcessing/venv/Lib/site-packages/wheel-0.35.1.dist-info/entry_points.txt
RFDetect/DataProcessing/venv/Lib/site-packages/wheel-0.35.1.dist-info/top_level.txt
