Metadata-Version: 2.1
Name: RFDetect
Version: 0.0.1
Summary: a python package to use Random Forest module to detect XSS.
Home-page: https://github.ccs.neu.edu/Capstone-Team/RandomForest
Author: Chen
Author-email: chen.rui@northeastern.edu
License: UNKNOWN
Platform: UNKNOWN
Classifier: Programming Language :: Python :: 3
Classifier: License :: OSI Approved :: MIT License
Classifier: Operating System :: OS Independent
